{
  "heroes": [
    {
      "id": 1,
      "name": "Первый герой",
      "description": "Первый герой в рейтинге!",
      "element": "fire"
    },
    {
      "id": "f1ab1673-d03d-4430-b38c-01bf00bc45c4",
      "name": "dsfsdf",
      "description": "dsfsdfsdf",
      "element": "water"
    },
    {
      "id": "99e01819-4a3d-4b6b-9b01-b2d262714e28",
      "name": "sadasd",
      "description": "asdsad",
      "element": "fire"
    },
    {
      "id": "8716e5dc-c8de-4188-a46e-daa8bfad7d15",
      "name": "RGRG",
      "description": "ERGREG",
      "element": "fire"
    },
    {
      "id": "8e93d526-15e6-4b15-af1f-c5f68ea77361",
      "name": "ERGERGERGER",
      "description": "RWEREWR",
      "element": "wind"
    }
  ],
  "filters": [
    {
      "label": "Все",
      "value": "all"
    },
    {
      "label": "Огонь",
      "value": "fire"
    },
    {
      "label": "Вода",
      "value": "water"
    },
    {
      "label": "Ветер",
      "value": "wind"
    },
    {
      "label": "Земля",
      "value": "earth"
    }
  ]
}